{
  "_meta": {
    "version": "1.0.0",
    "lastUpdated": "2026-03-19T13:19:00.074Z",
    "description": "Community-shared ad blocking rules for Stream Ad Blocker",
    "contributors": 4,
    "totalRules": 6
  },
  "twitch": {
    "selectors": [
      ".ad-banner-test",
      ".sponsored-content-test",
      ".legit-selector"
    ],
    "markers": [
      "Commercial Break"
    ],
    "gqlBlocks": [
      "AdAnalytics"
    ],
    "blockedUrls": [
      "ads.example.com"
    ]
  },
  "youtube": {
    "selectors": [],
    "markers": [],
    "gqlBlocks": [],
    "blockedUrls": []
  },
  "kick": {
    "selectors": [],
    "markers": [],
    "gqlBlocks": [],
    "blockedUrls": []
  },
  "facebook": {
    "selectors": [],
    "markers": [],
    "gqlBlocks": [],
    "blockedUrls": []
  }
}
